taglib.cpython-37m-x86_64-linux-gnu.so
pyprinttags.py
pytaglib_wheel.libs/libtag-26bc3dff.so.1.17.0
pytaglib_wheel.libs/libicudata-79cf9efa.so.57.1
pytaglib_wheel.libs/libicuuc-5743fca1.so.57.1
pytaglib_wheel-1.5.0.dist-info/WHEEL
pytaglib_wheel-1.5.0.dist-info/COPYING
pytaglib_wheel-1.5.0.dist-info/RECORD
pytaglib_wheel-1.5.0.dist-info/METADATA
pytaglib_wheel-1.5.0.dist-info/entry_points.txt
pytaglib_wheel-1.5.0.dist-info/top_level.txt
