Metadata-Version: 2.1
Name: pytaglib-wheel
Version: 1.5.0
Summary: cross-platform, Python audio metadata ("tagging") library based on TagLib
Home-page: http://github.com/supermihi/pytaglib
Author: Michael Helmling
Author-email: michaelhelmling@posteo.de
License: GPLv3+
Classifier: Development Status :: 5 - Production/Stable
Classifier: Intended Audience :: Developers
Classifier: License :: OSI Approved :: GNU General Public License v3 or later (GPLv3+)
Classifier: Natural Language :: English
Classifier: Operating System :: OS Independent
Classifier: Programming Language :: Cython
Classifier: Programming Language :: Python
Classifier: Programming Language :: Python :: 3
Classifier: Topic :: Software Development :: Libraries :: Python Modules
Requires-Python: >=3.6
License-File: COPYING
Provides-Extra: tests
Requires-Dist: pytest ; extra == 'tests'
